file_strategies/__init__.py
file_strategies/file_strategies.py
file_strategies-1.0.3.dist-info/METADATA
file_strategies-1.0.3.dist-info/RECORD
file_strategies-1.0.3.dist-info/WHEEL
file_strategies-1.0.3.dist-info/top_level.txt
test/__init__.py
test/test_file_strategies.py
