Metadata-Version: 2.1
Name: file-strategies
Version: 1.0.3
Summary: Strategy classes for access to various file sources (S3, local, etc.). Python 3 compatible.
Home-page: https://github.com/CarbonLighthouse/file-strategies
Author: CarbonLighthouse
License: MIT
Keywords: s3 file aws s3file fs local
Platform: UNKNOWN
Requires-Python: >=3
Requires-Dist: boto3 (<2.0.0,>=1.4.7)
